aws_secrets/__init__.py
django_aws_secrets_manager-0.1.5.dist-info/LICENSE
django_aws_secrets_manager-0.1.5.dist-info/METADATA
django_aws_secrets_manager-0.1.5.dist-info/WHEEL
django_aws_secrets_manager-0.1.5.dist-info/top_level.txt
django_aws_secrets_manager-0.1.5.dist-info/zip-safe
django_aws_secrets_manager-0.1.5.dist-info/RECORD
